config.py
config_manager.py
vritraai.py
vritraai-0.30.1.dist-info/licenses/LICENSE
vritraai-0.30.1.dist-info/METADATA
vritraai-0.30.1.dist-info/WHEEL
vritraai-0.30.1.dist-info/entry_points.txt
vritraai-0.30.1.dist-info/top_level.txt
vritraai-0.30.1.dist-info/RECORD
