Metadata-Version: 2.4
Name: vritraai
Version: 0.30.1
Summary: An intelligent, AI-enhanced terminal shell with advanced features, beautiful theming, and powerful command execution capabilities
Home-page: https://github.com/VritraSecz/VritraAI
Author: Alex Butler
Author-email: Alex Butler <contact@vritrasec.com>
Maintainer-email: Alex Butler <contact@vritrasec.com>
License: MIT
Project-URL: Homepage, https://github.com/VritraSecz/VritraAI
Project-URL: Documentation, https://vritraai.vritrasec.com/
Project-URL: Repository, https://github.com/VritraSecz/VritraAI
Project-URL: Bug Reports, https://github.com/VritraSecz/VritraAI/issues
Project-URL: Website, https://vritrasec.com
Keywords: terminal,shell,ai,cli,command-line,assistant,automation
Classifier: Development Status :: 4 - Beta
Classifier: Intended Audience :: Developers
Classifier: Intended Audience :: System Administrators
Classifier: Topic :: System :: Shells
Classifier: Topic :: System :: System Shells
Classifier: Topic :: Terminals
Classifier: Topic :: Utilities
Classifier: License :: OSI Approved :: MIT License
Classifier: Programming Language :: Python :: 3
Classifier: Programming Language :: Python :: 3.7
Classifier: Programming Language :: Python :: 3.8
Classifier: Programming Language :: Python :: 3.9
Classifier: Programming Language :: Python :: 3.10
Classifier: Programming Language :: Python :: 3.11
Classifier: Programming Language :: Python :: 3.12
Classifier: Operating System :: POSIX :: Linux
Classifier: Operating System :: MacOS
Classifier: Environment :: Console
Requires-Python: >=3.7
License-File: LICENSE
Requires-Dist: openai==0.28.0
Requires-Dist: requests>=2.28.0
Requires-Dist: prompt-toolkit>=3.0.0
Requires-Dist: rich>=13.0.0
Provides-Extra: optional
Requires-Dist: pygments>=2.13.0; extra == "optional"
Requires-Dist: psutil>=5.9.0; extra == "optional"
Provides-Extra: formatting
Requires-Dist: black>=23.0.0; extra == "formatting"
Requires-Dist: autopep8>=2.0.0; extra == "formatting"
Provides-Extra: all
Requires-Dist: pygments>=2.13.0; extra == "all"
Requires-Dist: psutil>=5.9.0; extra == "all"
Requires-Dist: black>=23.0.0; extra == "all"
Requires-Dist: autopep8>=2.0.0; extra == "all"
Dynamic: author
Dynamic: home-page
Dynamic: license-file
Dynamic: requires-python
